{"validation":{"status":{"name":"Ok","value":0,"category":0,"description":"","helpUrl":"For more reference visit http://comtrade.un.org/data/dev/portal/"},"message":null,"count":{"value":9,"started":"2018-05-20T00:49:13.2638207-04:00","finished":"2018-05-20T00:49:13.4228207-04:00","durationSeconds":0.159},"datasetTimer":{"started":"2018-05-20T00:49:13.2638207-04:00","finished":"2018-05-20T00:49:13.6408207-04:00","durationSeconds":0.377}},"dataset":[{"pfCode":"S1","yr":2007,"period":2007,"periodDesc":"2007","aggrLevel":3,"IsLeaf":0,"rgCode":1,"rgDesc":"Import","rtCode":470,"rtTitle":"Malta","rt3ISO":"MLT","ptCode":0,"ptTitle":"World","pt3ISO":"WLD","ptCode2":null,"ptTitle2":"","pt3ISO2":"","cstCode":"","cstDesc":"","motCode":"","motDesc":"","cmdCode":"673","cmdDescE":"Iron and steel bars,rods,angles,shapes,sections","qtCode":8,"qtDesc":"Weight in kilograms","qtAltCode":null,"qtAltDesc":"","TradeQuantity":50810364,"AltQuantity":null,"NetWeight":50810364,"GrossWeight":null,"TradeValue":35150644,"CIFValue":null,"FOBValue":null,"estCode":0},{"pfCode":"S1","yr":2007,"period":2007,"periodDesc":"2007","aggrLevel":3,"IsLeaf":0,"rgCode":2,"rgDesc":"Export","rtCode":470,"rtTitle":"Malta","rt3ISO":"MLT","ptCode":0,"ptTitle":"World","pt3ISO":"WLD","ptCode2":null,"ptTitle2":"","pt3ISO2":"","cstCode":"","cstDesc":"","motCode":"","motDesc":"","cmdCode":"673","cmdDescE":"Iron and steel bars,rods,angles,shapes,sections","qtCode":8,"qtDesc":"Weight in kilograms","qtAltCode":null,"qtAltDesc":"","TradeQuantity":16843,"AltQuantity":null,"NetWeight":16843,"GrossWeight":null,"TradeValue":31508,"CIFValue":null,"FOBValue":null,"estCode":0},{"pfCode":"S1","yr":2007,"period":2007,"periodDesc":"2007","aggrLevel":3,"IsLeaf":0,"rgCode":1,"rgDesc":"Import","rtCode":470,"rtTitle":"Malta","rt3ISO":"MLT","ptCode":0,"ptTitle":"World","pt3ISO":"WLD","ptCode2":null,"ptTitle2":"","pt3ISO2":"","cstCode":"","cstDesc":"","motCode":"","motDesc":"","cmdCode":"674","cmdDescE":"Universals,plates and sheets of iron or steel","qtCode":8,"qtDesc":"Weight in kilograms","qtAltCode":null,"qtAltDesc":"","TradeQuantity":11751310,"AltQuantity":null,"NetWeight":11751310,"GrossWeight":null,"TradeValue":26146038,"CIFValue":null,"FOBValue":null,"estCode":0},{"pfCode":"S1","yr":2007,"period":2007,"periodDesc":"2007","aggrLevel":3,"IsLeaf":0,"rgCode":2,"rgDesc":"Export","rtCode":470,"rtTitle":"Malta","rt3ISO":"MLT","ptCode":0,"ptTitle":"World","pt3ISO":"WLD","ptCode2":null,"ptTitle2":"","pt3ISO2":"","cstCode":"","cstDesc":"","motCode":"","motDesc":"","cmdCode":"674","cmdDescE":"Universals,plates and sheets of iron or steel","qtCode":8,"qtDesc":"Weight in kilograms","qtAltCode":null,"qtAltDesc":"","TradeQuantity":423055,"AltQuantity":null,"NetWeight":423055,"GrossWeight":null,"TradeValue":178980,"CIFValue":null,"FOBValue":null,"estCode":0},{"pfCode":"S1","yr":2007,"period":2007,"periodDesc":"2007","aggrLevel":3,"IsLeaf":0,"rgCode":1,"rgDesc":"Import","rtCode":470,"rtTitle":"Malta","rt3ISO":"MLT","ptCode":0,"ptTitle":"World","pt3ISO":"WLD","ptCode2":null,"ptTitle2":"","pt3ISO2":"","cstCode":"","cstDesc":"","motCode":"","motDesc":"","cmdCode":"676","cmdDescE":"Rails & rlwy track constr mat. Of iron or steel","qtCode":8,"qtDesc":"Weight in kilograms","qtAltCode":null,"qtAltDesc":"","TradeQuantity":155,"AltQuantity":null,"NetWeight":155,"GrossWeight":null,"TradeValue":3976,"CIFValue":null,"FOBValue":null,"estCode":0},{"pfCode":"S1","yr":2007,"period":2007,"periodDesc":"2007","aggrLevel":3,"IsLeaf":0,"rgCode":1,"rgDesc":"Import","rtCode":470,"rtTitle":"Malta","rt3ISO":"MLT","ptCode":0,"ptTitle":"World","pt3ISO":"WLD","ptCode2":null,"ptTitle2":"","pt3ISO2":"","cstCode":"","cstDesc":"","motCode":"","motDesc":"","cmdCode":"677","cmdDescE":"Iron and steel wire, excluding wire rod","qtCode":8,"qtDesc":"Weight in kilograms","qtAltCode":null,"qtAltDesc":"","TradeQuantity":1810244,"AltQuantity":null,"NetWeight":1810244,"GrossWeight":null,"TradeValue":1443970,"CIFValue":null,"FOBValue":null,"estCode":0},{"pfCode":"S1","yr":2007,"period":2007,"periodDesc":"2007","aggrLevel":3,"IsLeaf":0,"rgCode":2,"rgDesc":"Export","rtCode":470,"rtTitle":"Malta","rt3ISO":"MLT","ptCode":0,"ptTitle":"World","pt3ISO":"WLD","ptCode2":null,"ptTitle2":"","pt3ISO2":"","cstCode":"","cstDesc":"","motCode":"","motDesc":"","cmdCode":"677","cmdDescE":"Iron and steel wire, excluding wire rod","qtCode":8,"qtDesc":"Weight in kilograms","qtAltCode":null,"qtAltDesc":"","TradeQuantity":3775,"AltQuantity":null,"NetWeight":3775,"GrossWeight":null,"TradeValue":6083,"CIFValue":null,"FOBValue":null,"estCode":0},{"pfCode":"S1","yr":2007,"period":2007,"periodDesc":"2007","aggrLevel":3,"IsLeaf":0,"rgCode":1,"rgDesc":"Import","rtCode":470,"rtTitle":"Malta","rt3ISO":"MLT","ptCode":0,"ptTitle":"World","pt3ISO":"WLD","ptCode2":null,"ptTitle2":"","pt3ISO2":"","cstCode":"","cstDesc":"","motCode":"","motDesc":"","cmdCode":"678","cmdDescE":"Tubes,pipes and fittings of iron or steel","qtCode":8,"qtDesc":"Weight in kilograms","qtAltCode":null,"qtAltDesc":"","TradeQuantity":5543589,"AltQuantity":null,"NetWeight":5543589,"GrossWeight":null,"TradeValue":11286199,"CIFValue":null,"FOBValue":null,"estCode":0},{"pfCode":"S1","yr":2007,"period":2007,"periodDesc":"2007","aggrLevel":3,"IsLeaf":0,"rgCode":2,"rgDesc":"Export","rtCode":470,"rtTitle":"Malta","rt3ISO":"MLT","ptCode":0,"ptTitle":"World","pt3ISO":"WLD","ptCode2":null,"ptTitle2":"","pt3ISO2":"","cstCode":"","cstDesc":"","motCode":"","motDesc":"","cmdCode":"678","cmdDescE":"Tubes,pipes and fittings of iron or steel","qtCode":8,"qtDesc":"Weight in kilograms","qtAltCode":null,"qtAltDesc":"","TradeQuantity":151196,"AltQuantity":null,"NetWeight":151196,"GrossWeight":null,"TradeValue":274892,"CIFValue":null,"FOBValue":null,"estCode":0}]}