{"validation":{"status":{"name":"Ok","value":0,"category":0,"description":"","helpUrl":"For more reference visit http://comtrade.un.org/data/dev/portal/"},"message":null,"count":{"value":4,"started":"2018-05-29T07:38:25.0709002-04:00","finished":"2018-05-29T07:38:26.0579989-04:00","durationSeconds":0.9870987},"datasetTimer":{"started":"2018-05-29T07:38:25.0709002-04:00","finished":"2018-05-29T07:38:27.5801511-04:00","durationSeconds":2.5092509}},"dataset":[{"pfCode":"S1","yr":2009,"period":2009,"periodDesc":"2009","aggrLevel":4,"IsLeaf":0,"rgCode":1,"rgDesc":"Import","rtCode":528,"rtTitle":"Netherlands","rt3ISO":"NLD","ptCode":0,"ptTitle":"World","pt3ISO":"WLD","ptCode2":null,"ptTitle2":"","pt3ISO2":"","cstCode":"","cstDesc":"","motCode":"","motDesc":"","cmdCode":"2820","cmdDescE":"Iron & steel scrap","qtCode":8,"qtDesc":"Weight in kilograms","qtAltCode":null,"qtAltDesc":"","TradeQuantity":1287417733,"AltQuantity":null,"NetWeight":1287417733,"GrossWeight":null,"TradeValue":1101683470,"CIFValue":null,"FOBValue":null,"estCode":6},{"pfCode":"S1","yr":2009,"period":2009,"periodDesc":"2009","aggrLevel":4,"IsLeaf":0,"rgCode":2,"rgDesc":"Export","rtCode":528,"rtTitle":"Netherlands","rt3ISO":"NLD","ptCode":0,"ptTitle":"World","pt3ISO":"WLD","ptCode2":null,"ptTitle2":"","pt3ISO2":"","cstCode":"","cstDesc":"","motCode":"","motDesc":"","cmdCode":"2820","cmdDescE":"Iron & steel scrap","qtCode":8,"qtDesc":"Weight in kilograms","qtAltCode":null,"qtAltDesc":"","TradeQuantity":3169779452,"AltQuantity":null,"NetWeight":3169779452,"GrossWeight":null,"TradeValue":2105304016,"CIFValue":null,"FOBValue":null,"estCode":6},{"pfCode":"S1","yr":2009,"period":2009,"periodDesc":"2009","aggrLevel":4,"IsLeaf":1,"rgCode":1,"rgDesc":"Import","rtCode":528,"rtTitle":"Netherlands","rt3ISO":"NLD","ptCode":0,"ptTitle":"World","pt3ISO":"WLD","ptCode2":null,"ptTitle2":"","pt3ISO2":"","cstCode":"","cstDesc":"","motCode":"","motDesc":"","cmdCode":"6712","cmdDescE":"Pig iron, including cast iron","qtCode":8,"qtDesc":"Weight in kilograms","qtAltCode":null,"qtAltDesc":"","TradeQuantity":122402643,"AltQuantity":null,"NetWeight":122402643,"GrossWeight":null,"TradeValue":76864492,"CIFValue":null,"FOBValue":null,"estCode":6},{"pfCode":"S1","yr":2009,"period":2009,"periodDesc":"2009","aggrLevel":4,"IsLeaf":1,"rgCode":2,"rgDesc":"Export","rtCode":528,"rtTitle":"Netherlands","rt3ISO":"NLD","ptCode":0,"ptTitle":"World","pt3ISO":"WLD","ptCode2":null,"ptTitle2":"","pt3ISO2":"","cstCode":"","cstDesc":"","motCode":"","motDesc":"","cmdCode":"6712","cmdDescE":"Pig iron, including cast iron","qtCode":8,"qtDesc":"Weight in kilograms","qtAltCode":null,"qtAltDesc":"","TradeQuantity":89714303,"AltQuantity":null,"NetWeight":89714303,"GrossWeight":null,"TradeValue":51880787,"CIFValue":null,"FOBValue":null,"estCode":6}]}