{"validation":{"status":{"name":"Ok","value":0,"category":0,"description":"","helpUrl":"For more reference visit http://comtrade.un.org/data/dev/portal/"},"message":null,"count":{"value":4,"started":"2018-05-29T07:04:26.3680503-04:00","finished":"2018-05-29T07:04:26.9491084-04:00","durationSeconds":0.5810581},"datasetTimer":{"started":"2018-05-29T07:04:26.3680503-04:00","finished":"2018-05-29T07:04:27.3991534-04:00","durationSeconds":1.0311031}},"dataset":[{"pfCode":"S1","yr":1999,"period":1999,"periodDesc":"1999","aggrLevel":4,"IsLeaf":0,"rgCode":1,"rgDesc":"Import","rtCode":40,"rtTitle":"Austria","rt3ISO":"AUT","ptCode":0,"ptTitle":"World","pt3ISO":"WLD","ptCode2":null,"ptTitle2":"","pt3ISO2":"","cstCode":"","cstDesc":"","motCode":"","motDesc":"","cmdCode":"2820","cmdDescE":"Iron & steel scrap","qtCode":8,"qtDesc":"Weight in kilograms","qtAltCode":null,"qtAltDesc":"","TradeQuantity":577824651,"AltQuantity":null,"NetWeight":577824651,"GrossWeight":null,"TradeValue":57436463,"CIFValue":null,"FOBValue":null,"estCode":0},{"pfCode":"S1","yr":1999,"period":1999,"periodDesc":"1999","aggrLevel":4,"IsLeaf":0,"rgCode":2,"rgDesc":"Export","rtCode":40,"rtTitle":"Austria","rt3ISO":"AUT","ptCode":0,"ptTitle":"World","pt3ISO":"WLD","ptCode2":null,"ptTitle2":"","pt3ISO2":"","cstCode":"","cstDesc":"","motCode":"","motDesc":"","cmdCode":"2820","cmdDescE":"Iron & steel scrap","qtCode":8,"qtDesc":"Weight in kilograms","qtAltCode":null,"qtAltDesc":"","TradeQuantity":556645798,"AltQuantity":null,"NetWeight":556645798,"GrossWeight":null,"TradeValue":57474513,"CIFValue":null,"FOBValue":null,"estCode":0},{"pfCode":"S1","yr":1999,"period":1999,"periodDesc":"1999","aggrLevel":4,"IsLeaf":1,"rgCode":1,"rgDesc":"Import","rtCode":40,"rtTitle":"Austria","rt3ISO":"AUT","ptCode":0,"ptTitle":"World","pt3ISO":"WLD","ptCode2":null,"ptTitle2":"","pt3ISO2":"","cstCode":"","cstDesc":"","motCode":"","motDesc":"","cmdCode":"6712","cmdDescE":"Pig iron, including cast iron","qtCode":8,"qtDesc":"Weight in kilograms","qtAltCode":null,"qtAltDesc":"","TradeQuantity":22503038,"AltQuantity":null,"NetWeight":22503038,"GrossWeight":null,"TradeValue":4178814,"CIFValue":null,"FOBValue":null,"estCode":0},{"pfCode":"S1","yr":1999,"period":1999,"periodDesc":"1999","aggrLevel":4,"IsLeaf":1,"rgCode":2,"rgDesc":"Export","rtCode":40,"rtTitle":"Austria","rt3ISO":"AUT","ptCode":0,"ptTitle":"World","pt3ISO":"WLD","ptCode2":null,"ptTitle2":"","pt3ISO2":"","cstCode":"","cstDesc":"","motCode":"","motDesc":"","cmdCode":"6712","cmdDescE":"Pig iron, including cast iron","qtCode":8,"qtDesc":"Weight in kilograms","qtAltCode":null,"qtAltDesc":"","TradeQuantity":723892,"AltQuantity":null,"NetWeight":723892,"GrossWeight":null,"TradeValue":578836,"CIFValue":null,"FOBValue":null,"estCode":0}]}