{"validation":{"status":{"name":"Ok","value":0,"category":0,"description":"","helpUrl":"For more reference visit http://comtrade.un.org/data/dev/portal/"},"message":null,"count":{"value":10,"started":"2018-05-20T00:53:05.2078207-04:00","finished":"2018-05-20T00:53:05.3928207-04:00","durationSeconds":0.185},"datasetTimer":{"started":"2018-05-20T00:53:05.2078207-04:00","finished":"2018-05-20T00:53:05.6718207-04:00","durationSeconds":0.46399999999999997}},"dataset":[{"pfCode":"S1","yr":2008,"period":2008,"periodDesc":"2008","aggrLevel":3,"IsLeaf":0,"rgCode":1,"rgDesc":"Import","rtCode":616,"rtTitle":"Poland","rt3ISO":"POL","ptCode":0,"ptTitle":"World","pt3ISO":"WLD","ptCode2":null,"ptTitle2":"","pt3ISO2":"","cstCode":"","cstDesc":"","motCode":"","motDesc":"","cmdCode":"673","cmdDescE":"Iron and steel bars,rods,angles,shapes,sections","qtCode":8,"qtDesc":"Weight in kilograms","qtAltCode":null,"qtAltDesc":"","TradeQuantity":1619080408,"AltQuantity":null,"NetWeight":1619080408,"GrossWeight":null,"TradeValue":1868414743,"CIFValue":null,"FOBValue":null,"estCode":6},{"pfCode":"S1","yr":2008,"period":2008,"periodDesc":"2008","aggrLevel":3,"IsLeaf":0,"rgCode":2,"rgDesc":"Export","rtCode":616,"rtTitle":"Poland","rt3ISO":"POL","ptCode":0,"ptTitle":"World","pt3ISO":"WLD","ptCode2":null,"ptTitle2":"","pt3ISO2":"","cstCode":"","cstDesc":"","motCode":"","motDesc":"","cmdCode":"673","cmdDescE":"Iron and steel bars,rods,angles,shapes,sections","qtCode":8,"qtDesc":"Weight in kilograms","qtAltCode":null,"qtAltDesc":"","TradeQuantity":2281708434,"AltQuantity":null,"NetWeight":2281708434,"GrossWeight":null,"TradeValue":2507558745,"CIFValue":null,"FOBValue":null,"estCode":6},{"pfCode":"S1","yr":2008,"period":2008,"periodDesc":"2008","aggrLevel":3,"IsLeaf":0,"rgCode":1,"rgDesc":"Import","rtCode":616,"rtTitle":"Poland","rt3ISO":"POL","ptCode":0,"ptTitle":"World","pt3ISO":"WLD","ptCode2":null,"ptTitle2":"","pt3ISO2":"","cstCode":"","cstDesc":"","motCode":"","motDesc":"","cmdCode":"674","cmdDescE":"Universals,plates and sheets of iron or steel","qtCode":8,"qtDesc":"Weight in kilograms","qtAltCode":null,"qtAltDesc":"","TradeQuantity":4104646212,"AltQuantity":null,"NetWeight":4104646212,"GrossWeight":null,"TradeValue":5348657950,"CIFValue":null,"FOBValue":null,"estCode":6},{"pfCode":"S1","yr":2008,"period":2008,"periodDesc":"2008","aggrLevel":3,"IsLeaf":0,"rgCode":2,"rgDesc":"Export","rtCode":616,"rtTitle":"Poland","rt3ISO":"POL","ptCode":0,"ptTitle":"World","pt3ISO":"WLD","ptCode2":null,"ptTitle2":"","pt3ISO2":"","cstCode":"","cstDesc":"","motCode":"","motDesc":"","cmdCode":"674","cmdDescE":"Universals,plates and sheets of iron or steel","qtCode":8,"qtDesc":"Weight in kilograms","qtAltCode":null,"qtAltDesc":"","TradeQuantity":995315440,"AltQuantity":null,"NetWeight":995315440,"GrossWeight":null,"TradeValue":1492508890,"CIFValue":null,"FOBValue":null,"estCode":6},{"pfCode":"S1","yr":2008,"period":2008,"periodDesc":"2008","aggrLevel":3,"IsLeaf":0,"rgCode":1,"rgDesc":"Import","rtCode":616,"rtTitle":"Poland","rt3ISO":"POL","ptCode":0,"ptTitle":"World","pt3ISO":"WLD","ptCode2":null,"ptTitle2":"","pt3ISO2":"","cstCode":"","cstDesc":"","motCode":"","motDesc":"","cmdCode":"676","cmdDescE":"Rails & rlwy track constr mat. Of iron or steel","qtCode":8,"qtDesc":"Weight in kilograms","qtAltCode":null,"qtAltDesc":"","TradeQuantity":43412890,"AltQuantity":null,"NetWeight":43412890,"GrossWeight":null,"TradeValue":62862507,"CIFValue":null,"FOBValue":null,"estCode":6},{"pfCode":"S1","yr":2008,"period":2008,"periodDesc":"2008","aggrLevel":3,"IsLeaf":0,"rgCode":2,"rgDesc":"Export","rtCode":616,"rtTitle":"Poland","rt3ISO":"POL","ptCode":0,"ptTitle":"World","pt3ISO":"WLD","ptCode2":null,"ptTitle2":"","pt3ISO2":"","cstCode":"","cstDesc":"","motCode":"","motDesc":"","cmdCode":"676","cmdDescE":"Rails & rlwy track constr mat. Of iron or steel","qtCode":8,"qtDesc":"Weight in kilograms","qtAltCode":null,"qtAltDesc":"","TradeQuantity":107756202,"AltQuantity":null,"NetWeight":107756202,"GrossWeight":null,"TradeValue":131879864,"CIFValue":null,"FOBValue":null,"estCode":0},{"pfCode":"S1","yr":2008,"period":2008,"periodDesc":"2008","aggrLevel":3,"IsLeaf":0,"rgCode":1,"rgDesc":"Import","rtCode":616,"rtTitle":"Poland","rt3ISO":"POL","ptCode":0,"ptTitle":"World","pt3ISO":"WLD","ptCode2":null,"ptTitle2":"","pt3ISO2":"","cstCode":"","cstDesc":"","motCode":"","motDesc":"","cmdCode":"677","cmdDescE":"Iron and steel wire, excluding wire rod","qtCode":8,"qtDesc":"Weight in kilograms","qtAltCode":null,"qtAltDesc":"","TradeQuantity":279199332,"AltQuantity":null,"NetWeight":279199332,"GrossWeight":null,"TradeValue":393458750,"CIFValue":null,"FOBValue":null,"estCode":0},{"pfCode":"S1","yr":2008,"period":2008,"periodDesc":"2008","aggrLevel":3,"IsLeaf":0,"rgCode":2,"rgDesc":"Export","rtCode":616,"rtTitle":"Poland","rt3ISO":"POL","ptCode":0,"ptTitle":"World","pt3ISO":"WLD","ptCode2":null,"ptTitle2":"","pt3ISO2":"","cstCode":"","cstDesc":"","motCode":"","motDesc":"","cmdCode":"677","cmdDescE":"Iron and steel wire, excluding wire rod","qtCode":8,"qtDesc":"Weight in kilograms","qtAltCode":null,"qtAltDesc":"","TradeQuantity":52413843,"AltQuantity":null,"NetWeight":52413843,"GrossWeight":null,"TradeValue":74246160,"CIFValue":null,"FOBValue":null,"estCode":6},{"pfCode":"S1","yr":2008,"period":2008,"periodDesc":"2008","aggrLevel":3,"IsLeaf":0,"rgCode":1,"rgDesc":"Import","rtCode":616,"rtTitle":"Poland","rt3ISO":"POL","ptCode":0,"ptTitle":"World","pt3ISO":"WLD","ptCode2":null,"ptTitle2":"","pt3ISO2":"","cstCode":"","cstDesc":"","motCode":"","motDesc":"","cmdCode":"678","cmdDescE":"Tubes,pipes and fittings of iron or steel","qtCode":8,"qtDesc":"Weight in kilograms","qtAltCode":null,"qtAltDesc":"","TradeQuantity":704567335,"AltQuantity":null,"NetWeight":704567335,"GrossWeight":null,"TradeValue":1497357598,"CIFValue":null,"FOBValue":null,"estCode":6},{"pfCode":"S1","yr":2008,"period":2008,"periodDesc":"2008","aggrLevel":3,"IsLeaf":0,"rgCode":2,"rgDesc":"Export","rtCode":616,"rtTitle":"Poland","rt3ISO":"POL","ptCode":0,"ptTitle":"World","pt3ISO":"WLD","ptCode2":null,"ptTitle2":"","pt3ISO2":"","cstCode":"","cstDesc":"","motCode":"","motDesc":"","cmdCode":"678","cmdDescE":"Tubes,pipes and fittings of iron or steel","qtCode":8,"qtDesc":"Weight in kilograms","qtAltCode":null,"qtAltDesc":"","TradeQuantity":341504425,"AltQuantity":null,"NetWeight":341504425,"GrossWeight":null,"TradeValue":913190173,"CIFValue":null,"FOBValue":null,"estCode":6}]}