{"validation":{"status":{"name":"Ok","value":0,"category":0,"description":"","helpUrl":"For more reference visit http://comtrade.un.org/data/dev/portal/"},"message":null,"count":{"value":12,"started":"2018-05-19T23:04:24.1413381-04:00","finished":"2018-05-19T23:04:24.6612341-04:00","durationSeconds":0.519896},"datasetTimer":{"started":"2018-05-19T23:04:24.1413381-04:00","finished":"2018-05-19T23:04:25.6590345-04:00","durationSeconds":1.5176964}},"dataset":[{"pfCode":"S1","yr":1977,"period":1977,"periodDesc":"1977","aggrLevel":3,"IsLeaf":0,"rgCode":1,"rgDesc":"Import","rtCode":752,"rtTitle":"Sweden","rt3ISO":"SWE","ptCode":0,"ptTitle":"World","pt3ISO":"WLD","ptCode2":null,"ptTitle2":"","pt3ISO2":"","cstCode":"","cstDesc":"","motCode":"","motDesc":"","cmdCode":"673","cmdDescE":"Iron and steel bars,rods,angles,shapes,sections","qtCode":8,"qtDesc":"Weight in kilograms","qtAltCode":null,"qtAltDesc":"","TradeQuantity":356650016,"AltQuantity":null,"NetWeight":356650016,"GrossWeight":null,"TradeValue":124182104,"CIFValue":null,"FOBValue":null,"estCode":0},{"pfCode":"S1","yr":1977,"period":1977,"periodDesc":"1977","aggrLevel":3,"IsLeaf":0,"rgCode":2,"rgDesc":"Export","rtCode":752,"rtTitle":"Sweden","rt3ISO":"SWE","ptCode":0,"ptTitle":"World","pt3ISO":"WLD","ptCode2":null,"ptTitle2":"","pt3ISO2":"","cstCode":"","cstDesc":"","motCode":"","motDesc":"","cmdCode":"673","cmdDescE":"Iron and steel bars,rods,angles,shapes,sections","qtCode":8,"qtDesc":"Weight in kilograms","qtAltCode":null,"qtAltDesc":"","TradeQuantity":600852800,"AltQuantity":null,"NetWeight":600852800,"GrossWeight":null,"TradeValue":281700544,"CIFValue":null,"FOBValue":null,"estCode":0},{"pfCode":"S1","yr":1977,"period":1977,"periodDesc":"1977","aggrLevel":3,"IsLeaf":0,"rgCode":1,"rgDesc":"Import","rtCode":752,"rtTitle":"Sweden","rt3ISO":"SWE","ptCode":0,"ptTitle":"World","pt3ISO":"WLD","ptCode2":null,"ptTitle2":"","pt3ISO2":"","cstCode":"","cstDesc":"","motCode":"","motDesc":"","cmdCode":"674","cmdDescE":"Universals,plates and sheets of iron or steel","qtCode":8,"qtDesc":"Weight in kilograms","qtAltCode":null,"qtAltDesc":"","TradeQuantity":864967296,"AltQuantity":null,"NetWeight":864967296,"GrossWeight":null,"TradeValue":316813280,"CIFValue":null,"FOBValue":null,"estCode":0},{"pfCode":"S1","yr":1977,"period":1977,"periodDesc":"1977","aggrLevel":3,"IsLeaf":0,"rgCode":2,"rgDesc":"Export","rtCode":752,"rtTitle":"Sweden","rt3ISO":"SWE","ptCode":0,"ptTitle":"World","pt3ISO":"WLD","ptCode2":null,"ptTitle2":"","pt3ISO2":"","cstCode":"","cstDesc":"","motCode":"","motDesc":"","cmdCode":"674","cmdDescE":"Universals,plates and sheets of iron or steel","qtCode":8,"qtDesc":"Weight in kilograms","qtAltCode":null,"qtAltDesc":"","TradeQuantity":616351680,"AltQuantity":null,"NetWeight":616351680,"GrossWeight":null,"TradeValue":366110592,"CIFValue":null,"FOBValue":null,"estCode":0},{"pfCode":"S1","yr":1977,"period":1977,"periodDesc":"1977","aggrLevel":3,"IsLeaf":0,"rgCode":1,"rgDesc":"Import","rtCode":752,"rtTitle":"Sweden","rt3ISO":"SWE","ptCode":0,"ptTitle":"World","pt3ISO":"WLD","ptCode2":null,"ptTitle2":"","pt3ISO2":"","cstCode":"","cstDesc":"","motCode":"","motDesc":"","cmdCode":"675","cmdDescE":"Hoop and strip of iron or steel","qtCode":8,"qtDesc":"Weight in kilograms","qtAltCode":null,"qtAltDesc":"","TradeQuantity":106876296,"AltQuantity":null,"NetWeight":106876296,"GrossWeight":null,"TradeValue":42467916,"CIFValue":null,"FOBValue":null,"estCode":0},{"pfCode":"S1","yr":1977,"period":1977,"periodDesc":"1977","aggrLevel":3,"IsLeaf":0,"rgCode":2,"rgDesc":"Export","rtCode":752,"rtTitle":"Sweden","rt3ISO":"SWE","ptCode":0,"ptTitle":"World","pt3ISO":"WLD","ptCode2":null,"ptTitle2":"","pt3ISO2":"","cstCode":"","cstDesc":"","motCode":"","motDesc":"","cmdCode":"675","cmdDescE":"Hoop and strip of iron or steel","qtCode":8,"qtDesc":"Weight in kilograms","qtAltCode":null,"qtAltDesc":"","TradeQuantity":81460032,"AltQuantity":null,"NetWeight":81460032,"GrossWeight":null,"TradeValue":141771968,"CIFValue":null,"FOBValue":null,"estCode":0},{"pfCode":"S1","yr":1977,"period":1977,"periodDesc":"1977","aggrLevel":3,"IsLeaf":0,"rgCode":1,"rgDesc":"Import","rtCode":752,"rtTitle":"Sweden","rt3ISO":"SWE","ptCode":0,"ptTitle":"World","pt3ISO":"WLD","ptCode2":null,"ptTitle2":"","pt3ISO2":"","cstCode":"","cstDesc":"","motCode":"","motDesc":"","cmdCode":"676","cmdDescE":"Rails & rlwy track constr mat. Of iron or steel","qtCode":8,"qtDesc":"Weight in kilograms","qtAltCode":null,"qtAltDesc":"","TradeQuantity":2480236,"AltQuantity":null,"NetWeight":2480236,"GrossWeight":null,"TradeValue":1916904,"CIFValue":null,"FOBValue":null,"estCode":0},{"pfCode":"S1","yr":1977,"period":1977,"periodDesc":"1977","aggrLevel":3,"IsLeaf":0,"rgCode":2,"rgDesc":"Export","rtCode":752,"rtTitle":"Sweden","rt3ISO":"SWE","ptCode":0,"ptTitle":"World","pt3ISO":"WLD","ptCode2":null,"ptTitle2":"","pt3ISO2":"","cstCode":"","cstDesc":"","motCode":"","motDesc":"","cmdCode":"676","cmdDescE":"Rails & rlwy track constr mat. Of iron or steel","qtCode":8,"qtDesc":"Weight in kilograms","qtAltCode":null,"qtAltDesc":"","TradeQuantity":20538160,"AltQuantity":null,"NetWeight":20538160,"GrossWeight":null,"TradeValue":6003437,"CIFValue":null,"FOBValue":null,"estCode":0},{"pfCode":"S1","yr":1977,"period":1977,"periodDesc":"1977","aggrLevel":3,"IsLeaf":0,"rgCode":1,"rgDesc":"Import","rtCode":752,"rtTitle":"Sweden","rt3ISO":"SWE","ptCode":0,"ptTitle":"World","pt3ISO":"WLD","ptCode2":null,"ptTitle2":"","pt3ISO2":"","cstCode":"","cstDesc":"","motCode":"","motDesc":"","cmdCode":"677","cmdDescE":"Iron and steel wire, excluding wire rod","qtCode":8,"qtDesc":"Weight in kilograms","qtAltCode":null,"qtAltDesc":"","TradeQuantity":20956912,"AltQuantity":null,"NetWeight":20956912,"GrossWeight":null,"TradeValue":14490802,"CIFValue":null,"FOBValue":null,"estCode":0},{"pfCode":"S1","yr":1977,"period":1977,"periodDesc":"1977","aggrLevel":3,"IsLeaf":0,"rgCode":2,"rgDesc":"Export","rtCode":752,"rtTitle":"Sweden","rt3ISO":"SWE","ptCode":0,"ptTitle":"World","pt3ISO":"WLD","ptCode2":null,"ptTitle2":"","pt3ISO2":"","cstCode":"","cstDesc":"","motCode":"","motDesc":"","cmdCode":"677","cmdDescE":"Iron and steel wire, excluding wire rod","qtCode":8,"qtDesc":"Weight in kilograms","qtAltCode":null,"qtAltDesc":"","TradeQuantity":67547744,"AltQuantity":null,"NetWeight":67547744,"GrossWeight":null,"TradeValue":104772568,"CIFValue":null,"FOBValue":null,"estCode":0},{"pfCode":"S1","yr":1977,"period":1977,"periodDesc":"1977","aggrLevel":3,"IsLeaf":0,"rgCode":1,"rgDesc":"Import","rtCode":752,"rtTitle":"Sweden","rt3ISO":"SWE","ptCode":0,"ptTitle":"World","pt3ISO":"WLD","ptCode2":null,"ptTitle2":"","pt3ISO2":"","cstCode":"","cstDesc":"","motCode":"","motDesc":"","cmdCode":"678","cmdDescE":"Tubes,pipes and fittings of iron or steel","qtCode":8,"qtDesc":"Weight in kilograms","qtAltCode":null,"qtAltDesc":"","TradeQuantity":227152960,"AltQuantity":null,"NetWeight":227152960,"GrossWeight":null,"TradeValue":153108592,"CIFValue":null,"FOBValue":null,"estCode":0},{"pfCode":"S1","yr":1977,"period":1977,"periodDesc":"1977","aggrLevel":3,"IsLeaf":0,"rgCode":2,"rgDesc":"Export","rtCode":752,"rtTitle":"Sweden","rt3ISO":"SWE","ptCode":0,"ptTitle":"World","pt3ISO":"WLD","ptCode2":null,"ptTitle2":"","pt3ISO2":"","cstCode":"","cstDesc":"","motCode":"","motDesc":"","cmdCode":"678","cmdDescE":"Tubes,pipes and fittings of iron or steel","qtCode":8,"qtDesc":"Weight in kilograms","qtAltCode":null,"qtAltDesc":"","TradeQuantity":212696688,"AltQuantity":null,"NetWeight":212696688,"GrossWeight":null,"TradeValue":265737424,"CIFValue":null,"FOBValue":null,"estCode":0}]}