{"validation":{"status":{"name":"Ok","value":0,"category":0,"description":"","helpUrl":"For more reference visit http://comtrade.un.org/data/dev/portal/"},"message":null,"count":{"value":10,"started":"2018-05-19T23:36:33.4798207-04:00","finished":"2018-05-19T23:36:33.9338207-04:00","durationSeconds":0.45399999999999996},"datasetTimer":{"started":"2018-05-19T23:36:33.4798207-04:00","finished":"2018-05-19T23:36:34.8088207-04:00","durationSeconds":1.329}},"dataset":[{"pfCode":"S1","yr":1988,"period":1988,"periodDesc":"1988","aggrLevel":3,"IsLeaf":0,"rgCode":1,"rgDesc":"Import","rtCode":280,"rtTitle":"Fmr Fed. Rep. of Germany","rt3ISO":"DEU","ptCode":0,"ptTitle":"World","pt3ISO":"WLD","ptCode2":null,"ptTitle2":"","pt3ISO2":"","cstCode":"","cstDesc":"","motCode":"","motDesc":"","cmdCode":"673","cmdDescE":"Iron and steel bars,rods,angles,shapes,sections","qtCode":8,"qtDesc":"Weight in kilograms","qtAltCode":null,"qtAltDesc":"","TradeQuantity":4479319552,"AltQuantity":null,"NetWeight":4479319552,"GrossWeight":null,"TradeValue":2142823040,"CIFValue":null,"FOBValue":null,"estCode":0},{"pfCode":"S1","yr":1988,"period":1988,"periodDesc":"1988","aggrLevel":3,"IsLeaf":0,"rgCode":2,"rgDesc":"Export","rtCode":280,"rtTitle":"Fmr Fed. Rep. of Germany","rt3ISO":"DEU","ptCode":0,"ptTitle":"World","pt3ISO":"WLD","ptCode2":null,"ptTitle2":"","pt3ISO2":"","cstCode":"","cstDesc":"","motCode":"","motDesc":"","cmdCode":"673","cmdDescE":"Iron and steel bars,rods,angles,shapes,sections","qtCode":8,"qtDesc":"Weight in kilograms","qtAltCode":null,"qtAltDesc":"","TradeQuantity":3140666880,"AltQuantity":null,"NetWeight":3140666880,"GrossWeight":null,"TradeValue":1834110976,"CIFValue":null,"FOBValue":null,"estCode":0},{"pfCode":"S1","yr":1988,"period":1988,"periodDesc":"1988","aggrLevel":3,"IsLeaf":0,"rgCode":1,"rgDesc":"Import","rtCode":280,"rtTitle":"Fmr Fed. Rep. of Germany","rt3ISO":"DEU","ptCode":0,"ptTitle":"World","pt3ISO":"WLD","ptCode2":null,"ptTitle2":"","pt3ISO2":"","cstCode":"","cstDesc":"","motCode":"","motDesc":"","cmdCode":"674","cmdDescE":"Universals,plates and sheets of iron or steel","qtCode":8,"qtDesc":"Weight in kilograms","qtAltCode":null,"qtAltDesc":"","TradeQuantity":4974813696,"AltQuantity":null,"NetWeight":4974813696,"GrossWeight":null,"TradeValue":3314647040,"CIFValue":null,"FOBValue":null,"estCode":0},{"pfCode":"S1","yr":1988,"period":1988,"periodDesc":"1988","aggrLevel":3,"IsLeaf":0,"rgCode":2,"rgDesc":"Export","rtCode":280,"rtTitle":"Fmr Fed. Rep. of Germany","rt3ISO":"DEU","ptCode":0,"ptTitle":"World","pt3ISO":"WLD","ptCode2":null,"ptTitle2":"","pt3ISO2":"","cstCode":"","cstDesc":"","motCode":"","motDesc":"","cmdCode":"674","cmdDescE":"Universals,plates and sheets of iron or steel","qtCode":8,"qtDesc":"Weight in kilograms","qtAltCode":null,"qtAltDesc":"","TradeQuantity":7661705728,"AltQuantity":null,"NetWeight":7661705728,"GrossWeight":null,"TradeValue":5294081024,"CIFValue":null,"FOBValue":null,"estCode":0},{"pfCode":"S1","yr":1988,"period":1988,"periodDesc":"1988","aggrLevel":3,"IsLeaf":0,"rgCode":1,"rgDesc":"Import","rtCode":280,"rtTitle":"Fmr Fed. Rep. of Germany","rt3ISO":"DEU","ptCode":0,"ptTitle":"World","pt3ISO":"WLD","ptCode2":null,"ptTitle2":"","pt3ISO2":"","cstCode":"","cstDesc":"","motCode":"","motDesc":"","cmdCode":"676","cmdDescE":"Rails & rlwy track constr mat. Of iron or steel","qtCode":8,"qtDesc":"Weight in kilograms","qtAltCode":null,"qtAltDesc":"","TradeQuantity":24966354,"AltQuantity":null,"NetWeight":24966354,"GrossWeight":null,"TradeValue":11721000,"CIFValue":null,"FOBValue":null,"estCode":0},{"pfCode":"S1","yr":1988,"period":1988,"periodDesc":"1988","aggrLevel":3,"IsLeaf":0,"rgCode":2,"rgDesc":"Export","rtCode":280,"rtTitle":"Fmr Fed. Rep. of Germany","rt3ISO":"DEU","ptCode":0,"ptTitle":"World","pt3ISO":"WLD","ptCode2":null,"ptTitle2":"","pt3ISO2":"","cstCode":"","cstDesc":"","motCode":"","motDesc":"","cmdCode":"676","cmdDescE":"Rails & rlwy track constr mat. Of iron or steel","qtCode":8,"qtDesc":"Weight in kilograms","qtAltCode":null,"qtAltDesc":"","TradeQuantity":145975056,"AltQuantity":null,"NetWeight":145975056,"GrossWeight":null,"TradeValue":88263000,"CIFValue":null,"FOBValue":null,"estCode":0},{"pfCode":"S1","yr":1988,"period":1988,"periodDesc":"1988","aggrLevel":3,"IsLeaf":0,"rgCode":1,"rgDesc":"Import","rtCode":280,"rtTitle":"Fmr Fed. Rep. of Germany","rt3ISO":"DEU","ptCode":0,"ptTitle":"World","pt3ISO":"WLD","ptCode2":null,"ptTitle2":"","pt3ISO2":"","cstCode":"","cstDesc":"","motCode":"","motDesc":"","cmdCode":"677","cmdDescE":"Iron and steel wire, excluding wire rod","qtCode":8,"qtDesc":"Weight in kilograms","qtAltCode":null,"qtAltDesc":"","TradeQuantity":371075744,"AltQuantity":null,"NetWeight":371075744,"GrossWeight":null,"TradeValue":342126016,"CIFValue":null,"FOBValue":null,"estCode":0},{"pfCode":"S1","yr":1988,"period":1988,"periodDesc":"1988","aggrLevel":3,"IsLeaf":0,"rgCode":2,"rgDesc":"Export","rtCode":280,"rtTitle":"Fmr Fed. Rep. of Germany","rt3ISO":"DEU","ptCode":0,"ptTitle":"World","pt3ISO":"WLD","ptCode2":null,"ptTitle2":"","pt3ISO2":"","cstCode":"","cstDesc":"","motCode":"","motDesc":"","cmdCode":"677","cmdDescE":"Iron and steel wire, excluding wire rod","qtCode":8,"qtDesc":"Weight in kilograms","qtAltCode":null,"qtAltDesc":"","TradeQuantity":327407680,"AltQuantity":null,"NetWeight":327407680,"GrossWeight":null,"TradeValue":339203008,"CIFValue":null,"FOBValue":null,"estCode":0},{"pfCode":"S1","yr":1988,"period":1988,"periodDesc":"1988","aggrLevel":3,"IsLeaf":0,"rgCode":1,"rgDesc":"Import","rtCode":280,"rtTitle":"Fmr Fed. Rep. of Germany","rt3ISO":"DEU","ptCode":0,"ptTitle":"World","pt3ISO":"WLD","ptCode2":null,"ptTitle2":"","pt3ISO2":"","cstCode":"","cstDesc":"","motCode":"","motDesc":"","cmdCode":"678","cmdDescE":"Tubes,pipes and fittings of iron or steel","qtCode":8,"qtDesc":"Weight in kilograms","qtAltCode":null,"qtAltDesc":"","TradeQuantity":1108361984,"AltQuantity":null,"NetWeight":1108361984,"GrossWeight":null,"TradeValue":1142137984,"CIFValue":null,"FOBValue":null,"estCode":0},{"pfCode":"S1","yr":1988,"period":1988,"periodDesc":"1988","aggrLevel":3,"IsLeaf":0,"rgCode":2,"rgDesc":"Export","rtCode":280,"rtTitle":"Fmr Fed. Rep. of Germany","rt3ISO":"DEU","ptCode":0,"ptTitle":"World","pt3ISO":"WLD","ptCode2":null,"ptTitle2":"","pt3ISO2":"","cstCode":"","cstDesc":"","motCode":"","motDesc":"","cmdCode":"678","cmdDescE":"Tubes,pipes and fittings of iron or steel","qtCode":8,"qtDesc":"Weight in kilograms","qtAltCode":null,"qtAltDesc":"","TradeQuantity":3444782336,"AltQuantity":null,"NetWeight":3444782336,"GrossWeight":null,"TradeValue":3275506944,"CIFValue":null,"FOBValue":null,"estCode":0}]}