{"validation":{"status":{"name":"Ok","value":0,"category":0,"description":"","helpUrl":"For more reference visit http://comtrade.un.org/data/dev/portal/"},"message":null,"count":{"value":10,"started":"2018-05-20T05:19:15.2188207-04:00","finished":"2018-05-20T05:19:15.4168207-04:00","durationSeconds":0.19799999999999998},"datasetTimer":{"started":"2018-05-20T05:19:15.2188207-04:00","finished":"2018-05-20T05:19:15.7648207-04:00","durationSeconds":0.54599999999999993}},"dataset":[{"pfCode":"S1","yr":2014,"period":2014,"periodDesc":"2014","aggrLevel":3,"IsLeaf":0,"rgCode":1,"rgDesc":"Import","rtCode":442,"rtTitle":"Luxembourg","rt3ISO":"LUX","ptCode":0,"ptTitle":"World","pt3ISO":"WLD","ptCode2":null,"ptTitle2":"","pt3ISO2":"","cstCode":"","cstDesc":"","motCode":"","motDesc":"","cmdCode":"673","cmdDescE":"Iron and steel bars,rods,angles,shapes,sections","qtCode":8,"qtDesc":"Weight in kilograms","qtAltCode":null,"qtAltDesc":"","TradeQuantity":238611470,"AltQuantity":null,"NetWeight":238611470,"GrossWeight":null,"TradeValue":196140650,"CIFValue":null,"FOBValue":null,"estCode":0},{"pfCode":"S1","yr":2014,"period":2014,"periodDesc":"2014","aggrLevel":3,"IsLeaf":0,"rgCode":2,"rgDesc":"Export","rtCode":442,"rtTitle":"Luxembourg","rt3ISO":"LUX","ptCode":0,"ptTitle":"World","pt3ISO":"WLD","ptCode2":null,"ptTitle2":"","pt3ISO2":"","cstCode":"","cstDesc":"","motCode":"","motDesc":"","cmdCode":"673","cmdDescE":"Iron and steel bars,rods,angles,shapes,sections","qtCode":8,"qtDesc":"Weight in kilograms","qtAltCode":null,"qtAltDesc":"","TradeQuantity":2079927336,"AltQuantity":null,"NetWeight":2079927336,"GrossWeight":null,"TradeValue":1732880791,"CIFValue":null,"FOBValue":null,"estCode":6},{"pfCode":"S1","yr":2014,"period":2014,"periodDesc":"2014","aggrLevel":3,"IsLeaf":0,"rgCode":1,"rgDesc":"Import","rtCode":442,"rtTitle":"Luxembourg","rt3ISO":"LUX","ptCode":0,"ptTitle":"World","pt3ISO":"WLD","ptCode2":null,"ptTitle2":"","pt3ISO2":"","cstCode":"","cstDesc":"","motCode":"","motDesc":"","cmdCode":"674","cmdDescE":"Universals,plates and sheets of iron or steel","qtCode":8,"qtDesc":"Weight in kilograms","qtAltCode":null,"qtAltDesc":"","TradeQuantity":761422587,"AltQuantity":null,"NetWeight":761422587,"GrossWeight":null,"TradeValue":470304524,"CIFValue":null,"FOBValue":null,"estCode":6},{"pfCode":"S1","yr":2014,"period":2014,"periodDesc":"2014","aggrLevel":3,"IsLeaf":0,"rgCode":2,"rgDesc":"Export","rtCode":442,"rtTitle":"Luxembourg","rt3ISO":"LUX","ptCode":0,"ptTitle":"World","pt3ISO":"WLD","ptCode2":null,"ptTitle2":"","pt3ISO2":"","cstCode":"","cstDesc":"","motCode":"","motDesc":"","cmdCode":"674","cmdDescE":"Universals,plates and sheets of iron or steel","qtCode":8,"qtDesc":"Weight in kilograms","qtAltCode":null,"qtAltDesc":"","TradeQuantity":765157995,"AltQuantity":null,"NetWeight":765157995,"GrossWeight":null,"TradeValue":684013012,"CIFValue":null,"FOBValue":null,"estCode":0},{"pfCode":"S1","yr":2014,"period":2014,"periodDesc":"2014","aggrLevel":3,"IsLeaf":0,"rgCode":1,"rgDesc":"Import","rtCode":442,"rtTitle":"Luxembourg","rt3ISO":"LUX","ptCode":0,"ptTitle":"World","pt3ISO":"WLD","ptCode2":null,"ptTitle2":"","pt3ISO2":"","cstCode":"","cstDesc":"","motCode":"","motDesc":"","cmdCode":"676","cmdDescE":"Rails & rlwy track constr mat. Of iron or steel","qtCode":8,"qtDesc":"Weight in kilograms","qtAltCode":null,"qtAltDesc":"","TradeQuantity":15600876,"AltQuantity":null,"NetWeight":15600876,"GrossWeight":null,"TradeValue":19362674,"CIFValue":null,"FOBValue":null,"estCode":0},{"pfCode":"S1","yr":2014,"period":2014,"periodDesc":"2014","aggrLevel":3,"IsLeaf":0,"rgCode":2,"rgDesc":"Export","rtCode":442,"rtTitle":"Luxembourg","rt3ISO":"LUX","ptCode":0,"ptTitle":"World","pt3ISO":"WLD","ptCode2":null,"ptTitle2":"","pt3ISO2":"","cstCode":"","cstDesc":"","motCode":"","motDesc":"","cmdCode":"676","cmdDescE":"Rails & rlwy track constr mat. Of iron or steel","qtCode":8,"qtDesc":"Weight in kilograms","qtAltCode":null,"qtAltDesc":"","TradeQuantity":59567081,"AltQuantity":null,"NetWeight":59567081,"GrossWeight":null,"TradeValue":91733886,"CIFValue":null,"FOBValue":null,"estCode":0},{"pfCode":"S1","yr":2014,"period":2014,"periodDesc":"2014","aggrLevel":3,"IsLeaf":0,"rgCode":1,"rgDesc":"Import","rtCode":442,"rtTitle":"Luxembourg","rt3ISO":"LUX","ptCode":0,"ptTitle":"World","pt3ISO":"WLD","ptCode2":null,"ptTitle2":"","pt3ISO2":"","cstCode":"","cstDesc":"","motCode":"","motDesc":"","cmdCode":"677","cmdDescE":"Iron and steel wire, excluding wire rod","qtCode":8,"qtDesc":"Weight in kilograms","qtAltCode":null,"qtAltDesc":"","TradeQuantity":22988379,"AltQuantity":null,"NetWeight":22988379,"GrossWeight":null,"TradeValue":23157882,"CIFValue":null,"FOBValue":null,"estCode":0},{"pfCode":"S1","yr":2014,"period":2014,"periodDesc":"2014","aggrLevel":3,"IsLeaf":0,"rgCode":2,"rgDesc":"Export","rtCode":442,"rtTitle":"Luxembourg","rt3ISO":"LUX","ptCode":0,"ptTitle":"World","pt3ISO":"WLD","ptCode2":null,"ptTitle2":"","pt3ISO2":"","cstCode":"","cstDesc":"","motCode":"","motDesc":"","cmdCode":"677","cmdDescE":"Iron and steel wire, excluding wire rod","qtCode":8,"qtDesc":"Weight in kilograms","qtAltCode":null,"qtAltDesc":"","TradeQuantity":132754875,"AltQuantity":null,"NetWeight":132754875,"GrossWeight":null,"TradeValue":173389850,"CIFValue":null,"FOBValue":null,"estCode":6},{"pfCode":"S1","yr":2014,"period":2014,"periodDesc":"2014","aggrLevel":3,"IsLeaf":0,"rgCode":1,"rgDesc":"Import","rtCode":442,"rtTitle":"Luxembourg","rt3ISO":"LUX","ptCode":0,"ptTitle":"World","pt3ISO":"WLD","ptCode2":null,"ptTitle2":"","pt3ISO2":"","cstCode":"","cstDesc":"","motCode":"","motDesc":"","cmdCode":"678","cmdDescE":"Tubes,pipes and fittings of iron or steel","qtCode":8,"qtDesc":"Weight in kilograms","qtAltCode":null,"qtAltDesc":"","TradeQuantity":12742783,"AltQuantity":null,"NetWeight":12742783,"GrossWeight":null,"TradeValue":56561983,"CIFValue":null,"FOBValue":null,"estCode":6},{"pfCode":"S1","yr":2014,"period":2014,"periodDesc":"2014","aggrLevel":3,"IsLeaf":0,"rgCode":2,"rgDesc":"Export","rtCode":442,"rtTitle":"Luxembourg","rt3ISO":"LUX","ptCode":0,"ptTitle":"World","pt3ISO":"WLD","ptCode2":null,"ptTitle2":"","pt3ISO2":"","cstCode":"","cstDesc":"","motCode":"","motDesc":"","cmdCode":"678","cmdDescE":"Tubes,pipes and fittings of iron or steel","qtCode":8,"qtDesc":"Weight in kilograms","qtAltCode":null,"qtAltDesc":"","TradeQuantity":3171130,"AltQuantity":null,"NetWeight":3171130,"GrossWeight":null,"TradeValue":17276226,"CIFValue":null,"FOBValue":null,"estCode":6}]}