{"validation":{"status":{"name":"Ok","value":0,"category":0,"description":"","helpUrl":"For more reference visit http://comtrade.un.org/data/dev/portal/"},"message":null,"count":{"value":2,"started":"2018-05-29T06:27:30.9445301-04:00","finished":"2018-05-29T06:27:31.2695626-04:00","durationSeconds":0.3250325},"datasetTimer":{"started":"2018-05-29T06:27:30.9445301-04:00","finished":"2018-05-29T06:27:31.693605-04:00","durationSeconds":0.7490749}},"dataset":[{"pfCode":"S1","yr":1985,"period":1985,"periodDesc":"1985","aggrLevel":4,"IsLeaf":0,"rgCode":2,"rgDesc":"Export","rtCode":470,"rtTitle":"Malta","rt3ISO":"MLT","ptCode":0,"ptTitle":"World","pt3ISO":"WLD","ptCode2":null,"ptTitle2":"","pt3ISO2":"","cstCode":"","cstDesc":"","motCode":"","motDesc":"","cmdCode":"2820","cmdDescE":"Iron & steel scrap","qtCode":8,"qtDesc":"Weight in kilograms","qtAltCode":null,"qtAltDesc":"","TradeQuantity":11797705,"AltQuantity":null,"NetWeight":11797705,"GrossWeight":null,"TradeValue":1267625,"CIFValue":null,"FOBValue":null,"estCode":0},{"pfCode":"S1","yr":1985,"period":1985,"periodDesc":"1985","aggrLevel":4,"IsLeaf":1,"rgCode":1,"rgDesc":"Import","rtCode":470,"rtTitle":"Malta","rt3ISO":"MLT","ptCode":0,"ptTitle":"World","pt3ISO":"WLD","ptCode2":null,"ptTitle2":"","pt3ISO2":"","cstCode":"","cstDesc":"","motCode":"","motDesc":"","cmdCode":"6712","cmdDescE":"Pig iron, including cast iron","qtCode":8,"qtDesc":"Weight in kilograms","qtAltCode":null,"qtAltDesc":"","TradeQuantity":535000,"AltQuantity":null,"NetWeight":535000,"GrossWeight":null,"TradeValue":258100,"CIFValue":null,"FOBValue":null,"estCode":0}]}