{"validation":{"status":{"name":"Ok","value":0,"category":0,"description":"","helpUrl":"For more reference visit http://comtrade.un.org/data/dev/portal/"},"message":null,"count":{"value":10,"started":"2018-05-20T00:06:01.5508207-04:00","finished":"2018-05-20T00:06:01.6968207-04:00","durationSeconds":0.146},"datasetTimer":{"started":"2018-05-20T00:06:01.5508207-04:00","finished":"2018-05-20T00:06:01.9708207-04:00","durationSeconds":0.42}},"dataset":[{"pfCode":"S1","yr":1996,"period":1996,"periodDesc":"1996","aggrLevel":3,"IsLeaf":0,"rgCode":1,"rgDesc":"Import","rtCode":642,"rtTitle":"Romania","rt3ISO":"ROU","ptCode":0,"ptTitle":"World","pt3ISO":"WLD","ptCode2":null,"ptTitle2":"","pt3ISO2":"","cstCode":"","cstDesc":"","motCode":"","motDesc":"","cmdCode":"673","cmdDescE":"Iron and steel bars,rods,angles,shapes,sections","qtCode":8,"qtDesc":"Weight in kilograms","qtAltCode":null,"qtAltDesc":"","TradeQuantity":36161060,"AltQuantity":null,"NetWeight":36161060,"GrossWeight":null,"TradeValue":23175000,"CIFValue":null,"FOBValue":null,"estCode":0},{"pfCode":"S1","yr":1996,"period":1996,"periodDesc":"1996","aggrLevel":3,"IsLeaf":0,"rgCode":2,"rgDesc":"Export","rtCode":642,"rtTitle":"Romania","rt3ISO":"ROU","ptCode":0,"ptTitle":"World","pt3ISO":"WLD","ptCode2":null,"ptTitle2":"","pt3ISO2":"","cstCode":"","cstDesc":"","motCode":"","motDesc":"","cmdCode":"673","cmdDescE":"Iron and steel bars,rods,angles,shapes,sections","qtCode":8,"qtDesc":"Weight in kilograms","qtAltCode":null,"qtAltDesc":"","TradeQuantity":629924608,"AltQuantity":null,"NetWeight":629924608,"GrossWeight":null,"TradeValue":181052992,"CIFValue":null,"FOBValue":null,"estCode":0},{"pfCode":"S1","yr":1996,"period":1996,"periodDesc":"1996","aggrLevel":3,"IsLeaf":0,"rgCode":1,"rgDesc":"Import","rtCode":642,"rtTitle":"Romania","rt3ISO":"ROU","ptCode":0,"ptTitle":"World","pt3ISO":"WLD","ptCode2":null,"ptTitle2":"","pt3ISO2":"","cstCode":"","cstDesc":"","motCode":"","motDesc":"","cmdCode":"674","cmdDescE":"Universals,plates and sheets of iron or steel","qtCode":8,"qtDesc":"Weight in kilograms","qtAltCode":null,"qtAltDesc":"","TradeQuantity":84004024,"AltQuantity":null,"NetWeight":84004024,"GrossWeight":null,"TradeValue":63779000,"CIFValue":null,"FOBValue":null,"estCode":0},{"pfCode":"S1","yr":1996,"period":1996,"periodDesc":"1996","aggrLevel":3,"IsLeaf":0,"rgCode":2,"rgDesc":"Export","rtCode":642,"rtTitle":"Romania","rt3ISO":"ROU","ptCode":0,"ptTitle":"World","pt3ISO":"WLD","ptCode2":null,"ptTitle2":"","pt3ISO2":"","cstCode":"","cstDesc":"","motCode":"","motDesc":"","cmdCode":"674","cmdDescE":"Universals,plates and sheets of iron or steel","qtCode":8,"qtDesc":"Weight in kilograms","qtAltCode":null,"qtAltDesc":"","TradeQuantity":1069701696,"AltQuantity":null,"NetWeight":1069701696,"GrossWeight":null,"TradeValue":375236000,"CIFValue":null,"FOBValue":null,"estCode":0},{"pfCode":"S1","yr":1996,"period":1996,"periodDesc":"1996","aggrLevel":3,"IsLeaf":0,"rgCode":1,"rgDesc":"Import","rtCode":642,"rtTitle":"Romania","rt3ISO":"ROU","ptCode":0,"ptTitle":"World","pt3ISO":"WLD","ptCode2":null,"ptTitle2":"","pt3ISO2":"","cstCode":"","cstDesc":"","motCode":"","motDesc":"","cmdCode":"676","cmdDescE":"Rails & rlwy track constr mat. Of iron or steel","qtCode":8,"qtDesc":"Weight in kilograms","qtAltCode":null,"qtAltDesc":"","TradeQuantity":7342581,"AltQuantity":null,"NetWeight":7342581,"GrossWeight":null,"TradeValue":5567000,"CIFValue":null,"FOBValue":null,"estCode":0},{"pfCode":"S1","yr":1996,"period":1996,"periodDesc":"1996","aggrLevel":3,"IsLeaf":0,"rgCode":2,"rgDesc":"Export","rtCode":642,"rtTitle":"Romania","rt3ISO":"ROU","ptCode":0,"ptTitle":"World","pt3ISO":"WLD","ptCode2":null,"ptTitle2":"","pt3ISO2":"","cstCode":"","cstDesc":"","motCode":"","motDesc":"","cmdCode":"676","cmdDescE":"Rails & rlwy track constr mat. Of iron or steel","qtCode":8,"qtDesc":"Weight in kilograms","qtAltCode":null,"qtAltDesc":"","TradeQuantity":17426000,"AltQuantity":null,"NetWeight":17426000,"GrossWeight":null,"TradeValue":7444000,"CIFValue":null,"FOBValue":null,"estCode":0},{"pfCode":"S1","yr":1996,"period":1996,"periodDesc":"1996","aggrLevel":3,"IsLeaf":0,"rgCode":1,"rgDesc":"Import","rtCode":642,"rtTitle":"Romania","rt3ISO":"ROU","ptCode":0,"ptTitle":"World","pt3ISO":"WLD","ptCode2":null,"ptTitle2":"","pt3ISO2":"","cstCode":"","cstDesc":"","motCode":"","motDesc":"","cmdCode":"677","cmdDescE":"Iron and steel wire, excluding wire rod","qtCode":8,"qtDesc":"Weight in kilograms","qtAltCode":null,"qtAltDesc":"","TradeQuantity":13918621,"AltQuantity":null,"NetWeight":13918621,"GrossWeight":null,"TradeValue":9692000,"CIFValue":null,"FOBValue":null,"estCode":0},{"pfCode":"S1","yr":1996,"period":1996,"periodDesc":"1996","aggrLevel":3,"IsLeaf":0,"rgCode":2,"rgDesc":"Export","rtCode":642,"rtTitle":"Romania","rt3ISO":"ROU","ptCode":0,"ptTitle":"World","pt3ISO":"WLD","ptCode2":null,"ptTitle2":"","pt3ISO2":"","cstCode":"","cstDesc":"","motCode":"","motDesc":"","cmdCode":"677","cmdDescE":"Iron and steel wire, excluding wire rod","qtCode":8,"qtDesc":"Weight in kilograms","qtAltCode":null,"qtAltDesc":"","TradeQuantity":102112000,"AltQuantity":null,"NetWeight":102112000,"GrossWeight":null,"TradeValue":32739000,"CIFValue":null,"FOBValue":null,"estCode":0},{"pfCode":"S1","yr":1996,"period":1996,"periodDesc":"1996","aggrLevel":3,"IsLeaf":0,"rgCode":1,"rgDesc":"Import","rtCode":642,"rtTitle":"Romania","rt3ISO":"ROU","ptCode":0,"ptTitle":"World","pt3ISO":"WLD","ptCode2":null,"ptTitle2":"","pt3ISO2":"","cstCode":"","cstDesc":"","motCode":"","motDesc":"","cmdCode":"678","cmdDescE":"Tubes,pipes and fittings of iron or steel","qtCode":8,"qtDesc":"Weight in kilograms","qtAltCode":null,"qtAltDesc":"","TradeQuantity":20396624,"AltQuantity":null,"NetWeight":20396624,"GrossWeight":null,"TradeValue":41754000,"CIFValue":null,"FOBValue":null,"estCode":0},{"pfCode":"S1","yr":1996,"period":1996,"periodDesc":"1996","aggrLevel":3,"IsLeaf":0,"rgCode":2,"rgDesc":"Export","rtCode":642,"rtTitle":"Romania","rt3ISO":"ROU","ptCode":0,"ptTitle":"World","pt3ISO":"WLD","ptCode2":null,"ptTitle2":"","pt3ISO2":"","cstCode":"","cstDesc":"","motCode":"","motDesc":"","cmdCode":"678","cmdDescE":"Tubes,pipes and fittings of iron or steel","qtCode":8,"qtDesc":"Weight in kilograms","qtAltCode":null,"qtAltDesc":"","TradeQuantity":223370320,"AltQuantity":null,"NetWeight":223370320,"GrossWeight":null,"TradeValue":137986000,"CIFValue":null,"FOBValue":null,"estCode":0}]}