{"validation":{"status":{"name":"Ok","value":0,"category":0,"description":"","helpUrl":"For more reference visit http://comtrade.un.org/data/dev/portal/"},"message":null,"count":{"value":4,"started":"2018-05-29T07:48:51.3825251-04:00","finished":"2018-05-29T07:48:52.451632-04:00","durationSeconds":1.0691069},"datasetTimer":{"started":"2018-05-29T07:48:51.3825251-04:00","finished":"2018-05-29T07:48:53.7477616-04:00","durationSeconds":2.3652365}},"dataset":[{"pfCode":"S1","yr":2012,"period":2012,"periodDesc":"2012","aggrLevel":4,"IsLeaf":0,"rgCode":1,"rgDesc":"Import","rtCode":620,"rtTitle":"Portugal","rt3ISO":"PRT","ptCode":0,"ptTitle":"World","pt3ISO":"WLD","ptCode2":null,"ptTitle2":"","pt3ISO2":"","cstCode":"","cstDesc":"","motCode":"","motDesc":"","cmdCode":"2820","cmdDescE":"Iron & steel scrap","qtCode":8,"qtDesc":"Weight in kilograms","qtAltCode":null,"qtAltDesc":"","TradeQuantity":1196297730,"AltQuantity":null,"NetWeight":1196297730,"GrossWeight":null,"TradeValue":469279678,"CIFValue":null,"FOBValue":null,"estCode":0},{"pfCode":"S1","yr":2012,"period":2012,"periodDesc":"2012","aggrLevel":4,"IsLeaf":0,"rgCode":2,"rgDesc":"Export","rtCode":620,"rtTitle":"Portugal","rt3ISO":"PRT","ptCode":0,"ptTitle":"World","pt3ISO":"WLD","ptCode2":null,"ptTitle2":"","pt3ISO2":"","cstCode":"","cstDesc":"","motCode":"","motDesc":"","cmdCode":"2820","cmdDescE":"Iron & steel scrap","qtCode":8,"qtDesc":"Weight in kilograms","qtAltCode":null,"qtAltDesc":"","TradeQuantity":240303402,"AltQuantity":null,"NetWeight":240303402,"GrossWeight":null,"TradeValue":133751326,"CIFValue":null,"FOBValue":null,"estCode":0},{"pfCode":"S1","yr":2012,"period":2012,"periodDesc":"2012","aggrLevel":4,"IsLeaf":1,"rgCode":1,"rgDesc":"Import","rtCode":620,"rtTitle":"Portugal","rt3ISO":"PRT","ptCode":0,"ptTitle":"World","pt3ISO":"WLD","ptCode2":null,"ptTitle2":"","pt3ISO2":"","cstCode":"","cstDesc":"","motCode":"","motDesc":"","cmdCode":"6712","cmdDescE":"Pig iron, including cast iron","qtCode":8,"qtDesc":"Weight in kilograms","qtAltCode":null,"qtAltDesc":"","TradeQuantity":1906030,"AltQuantity":null,"NetWeight":1906030,"GrossWeight":null,"TradeValue":1703287,"CIFValue":null,"FOBValue":null,"estCode":0},{"pfCode":"S1","yr":2012,"period":2012,"periodDesc":"2012","aggrLevel":4,"IsLeaf":1,"rgCode":2,"rgDesc":"Export","rtCode":620,"rtTitle":"Portugal","rt3ISO":"PRT","ptCode":0,"ptTitle":"World","pt3ISO":"WLD","ptCode2":null,"ptTitle2":"","pt3ISO2":"","cstCode":"","cstDesc":"","motCode":"","motDesc":"","cmdCode":"6712","cmdDescE":"Pig iron, including cast iron","qtCode":8,"qtDesc":"Weight in kilograms","qtAltCode":null,"qtAltDesc":"","TradeQuantity":17367254,"AltQuantity":null,"NetWeight":17367254,"GrossWeight":null,"TradeValue":8806568,"CIFValue":null,"FOBValue":null,"estCode":0}]}