{"validation":{"status":{"name":"Ok","value":0,"category":0,"description":"","helpUrl":"For more reference visit http://comtrade.un.org/data/dev/portal/"},"message":null,"count":{"value":11,"started":"2018-05-19T23:20:16.8898207-04:00","finished":"2018-05-19T23:20:17.0778207-04:00","durationSeconds":0.188},"datasetTimer":{"started":"2018-05-19T23:20:16.8898207-04:00","finished":"2018-05-19T23:20:17.2938207-04:00","durationSeconds":0.40399999999999997}},"dataset":[{"pfCode":"S1","yr":1982,"period":1982,"periodDesc":"1982","aggrLevel":3,"IsLeaf":0,"rgCode":1,"rgDesc":"Import","rtCode":200,"rtTitle":"Czechoslovakia","rt3ISO":"CSK","ptCode":0,"ptTitle":"World","pt3ISO":"WLD","ptCode2":null,"ptTitle2":"","pt3ISO2":"","cstCode":"","cstDesc":"","motCode":"","motDesc":"","cmdCode":"673","cmdDescE":"Iron and steel bars,rods,angles,shapes,sections","qtCode":1,"qtDesc":"No Quantity","qtAltCode":null,"qtAltDesc":"","TradeQuantity":0,"AltQuantity":null,"NetWeight":0,"GrossWeight":null,"TradeValue":58682632,"CIFValue":null,"FOBValue":null,"estCode":0},{"pfCode":"S1","yr":1982,"period":1982,"periodDesc":"1982","aggrLevel":3,"IsLeaf":0,"rgCode":2,"rgDesc":"Export","rtCode":200,"rtTitle":"Czechoslovakia","rt3ISO":"CSK","ptCode":0,"ptTitle":"World","pt3ISO":"WLD","ptCode2":null,"ptTitle2":"","pt3ISO2":"","cstCode":"","cstDesc":"","motCode":"","motDesc":"","cmdCode":"673","cmdDescE":"Iron and steel bars,rods,angles,shapes,sections","qtCode":1,"qtDesc":"No Quantity","qtAltCode":null,"qtAltDesc":"","TradeQuantity":0,"AltQuantity":null,"NetWeight":0,"GrossWeight":null,"TradeValue":1441684,"CIFValue":null,"FOBValue":null,"estCode":0},{"pfCode":"S1","yr":1982,"period":1982,"periodDesc":"1982","aggrLevel":3,"IsLeaf":0,"rgCode":1,"rgDesc":"Import","rtCode":200,"rtTitle":"Czechoslovakia","rt3ISO":"CSK","ptCode":0,"ptTitle":"World","pt3ISO":"WLD","ptCode2":null,"ptTitle2":"","pt3ISO2":"","cstCode":"","cstDesc":"","motCode":"","motDesc":"","cmdCode":"674","cmdDescE":"Universals,plates and sheets of iron or steel","qtCode":1,"qtDesc":"No Quantity","qtAltCode":null,"qtAltDesc":"","TradeQuantity":0,"AltQuantity":null,"NetWeight":0,"GrossWeight":null,"TradeValue":38117744,"CIFValue":null,"FOBValue":null,"estCode":0},{"pfCode":"S1","yr":1982,"period":1982,"periodDesc":"1982","aggrLevel":3,"IsLeaf":0,"rgCode":2,"rgDesc":"Export","rtCode":200,"rtTitle":"Czechoslovakia","rt3ISO":"CSK","ptCode":0,"ptTitle":"World","pt3ISO":"WLD","ptCode2":null,"ptTitle2":"","pt3ISO2":"","cstCode":"","cstDesc":"","motCode":"","motDesc":"","cmdCode":"674","cmdDescE":"Universals,plates and sheets of iron or steel","qtCode":1,"qtDesc":"No Quantity","qtAltCode":null,"qtAltDesc":"","TradeQuantity":0,"AltQuantity":null,"NetWeight":0,"GrossWeight":null,"TradeValue":8890000,"CIFValue":null,"FOBValue":null,"estCode":0},{"pfCode":"S1","yr":1982,"period":1982,"periodDesc":"1982","aggrLevel":3,"IsLeaf":0,"rgCode":1,"rgDesc":"Import","rtCode":200,"rtTitle":"Czechoslovakia","rt3ISO":"CSK","ptCode":0,"ptTitle":"World","pt3ISO":"WLD","ptCode2":null,"ptTitle2":"","pt3ISO2":"","cstCode":"","cstDesc":"","motCode":"","motDesc":"","cmdCode":"675","cmdDescE":"Hoop and strip of iron or steel","qtCode":1,"qtDesc":"No Quantity","qtAltCode":null,"qtAltDesc":"","TradeQuantity":0,"AltQuantity":null,"NetWeight":0,"GrossWeight":null,"TradeValue":14177601,"CIFValue":null,"FOBValue":null,"estCode":0},{"pfCode":"S1","yr":1982,"period":1982,"periodDesc":"1982","aggrLevel":3,"IsLeaf":0,"rgCode":2,"rgDesc":"Export","rtCode":200,"rtTitle":"Czechoslovakia","rt3ISO":"CSK","ptCode":0,"ptTitle":"World","pt3ISO":"WLD","ptCode2":null,"ptTitle2":"","pt3ISO2":"","cstCode":"","cstDesc":"","motCode":"","motDesc":"","cmdCode":"675","cmdDescE":"Hoop and strip of iron or steel","qtCode":1,"qtDesc":"No Quantity","qtAltCode":null,"qtAltDesc":"","TradeQuantity":0,"AltQuantity":null,"NetWeight":0,"GrossWeight":null,"TradeValue":49700556,"CIFValue":null,"FOBValue":null,"estCode":0},{"pfCode":"S1","yr":1982,"period":1982,"periodDesc":"1982","aggrLevel":3,"IsLeaf":0,"rgCode":2,"rgDesc":"Export","rtCode":200,"rtTitle":"Czechoslovakia","rt3ISO":"CSK","ptCode":0,"ptTitle":"World","pt3ISO":"WLD","ptCode2":null,"ptTitle2":"","pt3ISO2":"","cstCode":"","cstDesc":"","motCode":"","motDesc":"","cmdCode":"676","cmdDescE":"Rails & rlwy track constr mat. Of iron or steel","qtCode":1,"qtDesc":"No Quantity","qtAltCode":null,"qtAltDesc":"","TradeQuantity":0,"AltQuantity":null,"NetWeight":0,"GrossWeight":null,"TradeValue":9444051,"CIFValue":null,"FOBValue":null,"estCode":0},{"pfCode":"S1","yr":1982,"period":1982,"periodDesc":"1982","aggrLevel":3,"IsLeaf":0,"rgCode":1,"rgDesc":"Import","rtCode":200,"rtTitle":"Czechoslovakia","rt3ISO":"CSK","ptCode":0,"ptTitle":"World","pt3ISO":"WLD","ptCode2":null,"ptTitle2":"","pt3ISO2":"","cstCode":"","cstDesc":"","motCode":"","motDesc":"","cmdCode":"677","cmdDescE":"Iron and steel wire, excluding wire rod","qtCode":1,"qtDesc":"No Quantity","qtAltCode":null,"qtAltDesc":"","TradeQuantity":0,"AltQuantity":null,"NetWeight":0,"GrossWeight":null,"TradeValue":3253520,"CIFValue":null,"FOBValue":null,"estCode":0},{"pfCode":"S1","yr":1982,"period":1982,"periodDesc":"1982","aggrLevel":3,"IsLeaf":0,"rgCode":2,"rgDesc":"Export","rtCode":200,"rtTitle":"Czechoslovakia","rt3ISO":"CSK","ptCode":0,"ptTitle":"World","pt3ISO":"WLD","ptCode2":null,"ptTitle2":"","pt3ISO2":"","cstCode":"","cstDesc":"","motCode":"","motDesc":"","cmdCode":"677","cmdDescE":"Iron and steel wire, excluding wire rod","qtCode":1,"qtDesc":"No Quantity","qtAltCode":null,"qtAltDesc":"","TradeQuantity":0,"AltQuantity":null,"NetWeight":0,"GrossWeight":null,"TradeValue":43463080,"CIFValue":null,"FOBValue":null,"estCode":0},{"pfCode":"S1","yr":1982,"period":1982,"periodDesc":"1982","aggrLevel":3,"IsLeaf":0,"rgCode":1,"rgDesc":"Import","rtCode":200,"rtTitle":"Czechoslovakia","rt3ISO":"CSK","ptCode":0,"ptTitle":"World","pt3ISO":"WLD","ptCode2":null,"ptTitle2":"","pt3ISO2":"","cstCode":"","cstDesc":"","motCode":"","motDesc":"","cmdCode":"678","cmdDescE":"Tubes,pipes and fittings of iron or steel","qtCode":1,"qtDesc":"No Quantity","qtAltCode":null,"qtAltDesc":"","TradeQuantity":0,"AltQuantity":null,"NetWeight":0,"GrossWeight":null,"TradeValue":31611194,"CIFValue":null,"FOBValue":null,"estCode":0},{"pfCode":"S1","yr":1982,"period":1982,"periodDesc":"1982","aggrLevel":3,"IsLeaf":0,"rgCode":2,"rgDesc":"Export","rtCode":200,"rtTitle":"Czechoslovakia","rt3ISO":"CSK","ptCode":0,"ptTitle":"World","pt3ISO":"WLD","ptCode2":null,"ptTitle2":"","pt3ISO2":"","cstCode":"","cstDesc":"","motCode":"","motDesc":"","cmdCode":"678","cmdDescE":"Tubes,pipes and fittings of iron or steel","qtCode":1,"qtDesc":"No Quantity","qtAltCode":null,"qtAltDesc":"","TradeQuantity":0,"AltQuantity":null,"NetWeight":0,"GrossWeight":null,"TradeValue":6734555,"CIFValue":null,"FOBValue":null,"estCode":0}]}